{
  "updated": "2026-05-29 05:15 UTC",
  "updated_kst": "2026-05-29 14:15 KST",
  "stocks": {
    "TSLA": {
      "price": 442.1,
      "change_pct": 1.96,
      "currency": "USD",
      "name": "Tesla",
      "flag": "🇺🇸"
    },
    "NVDA": {
      "price": 214.25,
      "change_pct": -0.28,
      "currency": "USD",
      "name": "NVIDIA",
      "flag": "🇺🇸"
    },
    "TM": {
      "price": 191.84,
      "change_pct": 0.92,
      "currency": "USD",
      "name": "Toyota",
      "flag": "🇯🇵"
    },
    "BYDDF": {
      "price": 11.54,
      "change_pct": -2.86,
      "currency": "USD",
      "name": "BYD",
      "flag": "🇨🇳"
    },
    "MBG.DE": {
      "price": 52.71,
      "change_pct": 3.52,
      "currency": "EUR",
      "name": "Mercedes",
      "flag": "🇩🇪"
    },
    "BMW.DE": {
      "price": 75.94,
      "change_pct": 0.9,
      "currency": "EUR",
      "name": "BMW",
      "flag": "🇩🇪"
    },
    "GM": {
      "price": 84.35,
      "change_pct": 5.72,
      "currency": "USD",
      "name": "GM",
      "flag": "🇺🇸"
    },
    "F": {
      "price": 16.65,
      "change_pct": 8.68,
      "currency": "USD",
      "name": "Ford",
      "flag": "🇺🇸"
    },
    "MBLY": {
      "price": 10.41,
      "change_pct": 4.1,
      "currency": "USD",
      "name": "Mobileye",
      "flag": "🇺🇸"
    },
    "BIDU": {
      "price": 132.05,
      "change_pct": 4.12,
      "currency": "USD",
      "name": "Baidu",
      "flag": "🇨🇳"
    },
    "VWAGY": {
      "price": 10.97,
      "change_pct": 2.14,
      "currency": "USD",
      "name": "Volkswagen",
      "flag": "🇩🇪"
    },
    "HMC": {
      "price": 27.29,
      "change_pct": 3.29,
      "currency": "USD",
      "name": "Honda",
      "flag": "🇯🇵"
    }
  },
  "news": {
    "unreal": [],
    "gis": [],
    "us_av": [],
    "china_av": [],
    "europe_av": [],
    "linkedin_av": []
  }
}