{
  "updated": "2026-06-19 06:23 UTC",
  "updated_kst": "2026-06-19 15:23 KST",
  "stocks": {
    "TSLA": {
      "price": 400.49,
      "change_pct": -1.03,
      "currency": "USD",
      "name": "Tesla",
      "flag": "🇺🇸"
    },
    "NVDA": {
      "price": 210.69,
      "change_pct": 1.58,
      "currency": "USD",
      "name": "NVIDIA",
      "flag": "🇺🇸"
    },
    "TM": {
      "price": 173.94,
      "change_pct": -2.39,
      "currency": "USD",
      "name": "Toyota",
      "flag": "🇯🇵"
    },
    "BYDDF": {
      "price": 10.33,
      "change_pct": -2.91,
      "currency": "USD",
      "name": "BYD",
      "flag": "🇨🇳"
    },
    "MBG.DE": {
      "price": 44.6,
      "change_pct": -8.76,
      "currency": "EUR",
      "name": "Mercedes",
      "flag": "🇩🇪"
    },
    "BMW.DE": {
      "price": 59.74,
      "change_pct": -12.02,
      "currency": "EUR",
      "name": "BMW",
      "flag": "🇩🇪"
    },
    "GM": {
      "price": 79.29,
      "change_pct": -3.9,
      "currency": "USD",
      "name": "GM",
      "flag": "🇺🇸"
    },
    "F": {
      "price": 14.06,
      "change_pct": -2.43,
      "currency": "USD",
      "name": "Ford",
      "flag": "🇺🇸"
    },
    "MBLY": {
      "price": 8.46,
      "change_pct": -12.06,
      "currency": "USD",
      "name": "Mobileye",
      "flag": "🇺🇸"
    },
    "BIDU": {
      "price": 111.76,
      "change_pct": -0.85,
      "currency": "USD",
      "name": "Baidu",
      "flag": "🇨🇳"
    },
    "VWAGY": {
      "price": 9.91,
      "change_pct": -3.97,
      "currency": "USD",
      "name": "Volkswagen",
      "flag": "🇩🇪"
    },
    "HMC": {
      "price": 26.26,
      "change_pct": -2.2,
      "currency": "USD",
      "name": "Honda",
      "flag": "🇯🇵"
    }
  },
  "news": {
    "unreal": [],
    "gis": [],
    "us_av": [],
    "china_av": [],
    "europe_av": [],
    "linkedin_av": []
  }
}